veb/__init__.py
veb/_core.py
veb/tests/__init__.py
veb/tests/test_core.py
veb-0.2.3.dist-info/METADATA
veb-0.2.3.dist-info/WHEEL
veb-0.2.3.dist-info/licenses/COPYING
veb-0.2.3.dist-info/RECORD
